{"artifact_hash":"e631cef46901625cbbe02359025dc10d036b913a8f7c821c631e9c14aea9be0e","artifact_type":"blueprint","payload":{"instruction_id":"ce121faf-a83a-4c7e-a944-1fd2c6613bba","intent_type":"generate_content","origin":"creator_core","payload":{"blueprint_type":"content_blueprint","content_type":"step_by_step_guide","outline":["plot_development","character_creation","story_outline","narrative_expansion"],"product_target":"creator","title":"Story"},"schema_version":"1.0","target_product":"creator","timestamp":"2026-06-05T09:04:29.703892+00:00"},"source_module_id":"creator_core"}